{
  "@context": "https://schema.org/",
  "@type": "Dataset",
  "dct:conformsTo": "http://mlcommons.org/croissant/1.0",
  "name": "Doctorates awarded to U.S. citizens and permanent residents, by race or ethnicity: 2021",
  "identifier": "NCSES-7662",
  "description": "Doctorates awarded to U.S. citizens and permanent residents, by race or ethnicity: 2021",
  "url": "https://example.org/datasets/ncses/tables/7662",
  "table_number": "B",
  "creator": {
    "@type": "Organization",
    "name": "National Center for Science and Engineering Statistics"
  },
  "schemaVersion": "https://w3id.org/croissant/schema/1.0",
  "distribution": {
    "@type": "DataDownload",
    "encodingFormat": "text/csv",
    "contentUrl": "https://example.org/datasets/ncses/tables/7662/data.csv"
  },
  "variableMeasured": [
    {
      "@type": "PropertyValue",
      "name": "race_and_ethnicity",
      "description": "Race and ethnicity hierarchy",
      "valueType": "string",
      "additionalProperty": [
        {
          "name": "hierarchical",
          "value": "true"
        },
        {
          "name": "maxHierarchyDepth",
          "value": "3"
        },
        {
          "name": "levelColumns",
          "value": "race_and_ethnicity_level_1, race_and_ethnicity_level_2, race_and_ethnicity_level_3"
        },
        {
          "name": "fullPathColumn",
          "value": "race_and_ethnicity_full_path"
        }
      ]
    },
    {
      "@type": "PropertyValue",
      "name": "field_number",
      "description": "Number",
      "valueType": "string",
      "unitText": "Number and percent"
    },
    {
      "@type": "PropertyValue",
      "name": "field_percent",
      "description": "Percent",
      "valueType": "string",
      "unitText": "Number and percent"
    }
  ],
  "structuralType": "table",
  "transformationNotes": {
    "cleaningOperations": [
      "HTML tag removal",
      "Hierarchy normalization",
      "Special value handling"
    ],
    "specialValues": {
      "i": "imputed value",
      "r": "revised value"
    }
  },
  "notes": "Percentages may not sum to 100 due to rounding.",
  "sources": "National Center for Science and Engineering Statistics, Survey of Earned Doctorates, 2021. Related detailed table 1-11."
}