{
  "@context": "https://schema.org/",
  "@type": "Dataset",
  "dct:conformsTo": "http://mlcommons.org/croissant/1.0",
  "name": "Labor force participation and unemployment of U.S. civilian population and LSDR population: 2015\u201319",
  "identifier": "NCSES-6273",
  "description": "Labor force participation and unemployment of U.S. civilian population and LSDR population: 2015\u201319",
  "url": "https://example.org/datasets/ncses/tables/6273",
  "table_number": "1",
  "creator": {
    "@type": "Organization",
    "name": "National Center for Science and Engineering Statistics"
  },
  "schemaVersion": "https://w3id.org/croissant/schema/1.0",
  "distribution": {
    "@type": "DataDownload",
    "encodingFormat": "text/csv",
    "contentUrl": "https://example.org/datasets/ncses/tables/6273/data.csv"
  },
  "variableMeasured": [
    {
      "@type": "PropertyValue",
      "name": "time_period",
      "description": "Time period of the measurement",
      "valueType": "string"
    },
    {
      "@type": "PropertyValue",
      "name": "labor_force_participation_characteristic",
      "description": "Labor force participation hierarchy",
      "valueType": "string",
      "additionalProperty": [
        {
          "name": "hierarchical",
          "value": "true"
        },
        {
          "name": "maxHierarchyDepth",
          "value": "2"
        },
        {
          "name": "levelColumns",
          "value": "labor_force_participation_level_1, labor_force_participation_level_2"
        }
      ]
    },
    {
      "@type": "PropertyValue",
      "name": "value",
      "description": "Measurement value",
      "valueType": "string",
      "unitText": "Percent"
    }
  ],
  "structuralType": "table",
  "transformationNotes": {
    "cleaningOperations": [
      "HTML tag removal",
      "Hierarchy normalization",
      "Special value handling"
    ],
    "specialValues": {
      "r": "revised value"
    }
  },
  "notes": "Labor force and unemployment statistics of U.S. civilian population are CPS 2015, 2017, and 2019 annual average employment status tables are available at https://www.bls.gov/charts/employment-situation/civilian-labor-force-participation-rate.htm\nand at https://www.bls.gov/charts/employment-situation/civilian-unemployment.htm. CPS definitions for U.S. civilian population and labor force are detailed at https://www.bls.gov/cps/definitions.htm#population.",
  "sources": "National Center for Science and Engineering Statistics, Survey of Doctorate Recipients longitudinal panel 2015\u201325 (LSDR 2015\u201319 data file).",
  "temporalCoverage": "20/20"
}