{
  "@context": "https://schema.org/",
  "@type": "Dataset",
  "dct:conformsTo": "http://mlcommons.org/croissant/1.0",
  "name": "Estimates and standard errors for SEH doctorate holders receiving an NSF award, by employment sector, sex, race, and ethnicity",
  "identifier": "NCSES-6995",
  "description": "Estimates and standard errors for SEH doctorate holders receiving an NSF award, by employment sector, sex, race, and ethnicity",
  "url": "https://example.org/datasets/ncses/tables/6995",
  "table_number": "B-3",
  "creator": {
    "@type": "Organization",
    "name": "National Center for Science and Engineering Statistics"
  },
  "schemaVersion": "https://w3id.org/croissant/schema/1.0",
  "distribution": {
    "@type": "DataDownload",
    "encodingFormat": "text/csv",
    "contentUrl": "https://example.org/datasets/ncses/tables/6995/data.csv"
  },
  "variableMeasured": [
    {
      "@type": "PropertyValue",
      "name": "employment_sector_sex_race_and_ethnicity",
      "description": "Employment sector, sex, race, and ethnicity hierarchy",
      "valueType": "string",
      "additionalProperty": [
        {
          "name": "hierarchical",
          "value": "true"
        },
        {
          "name": "maxHierarchyDepth",
          "value": "3"
        },
        {
          "name": "levelColumns",
          "value": "employment_sector_sex_race_and_ethnicity_level_1, employment_sector_sex_race_and_ethnicity_level_2, employment_sector_sex_race_and_ethnicity_level_3"
        },
        {
          "name": "fullPathColumn",
          "value": "employment_sector_sex_race_and_ethnicity_full_path"
        }
      ]
    },
    {
      "@type": "PropertyValue",
      "name": "field_estimates_nsf_award",
      "description": "Estimates Nsf Award",
      "valueType": "string",
      "unitText": "Number and percent"
    },
    {
      "@type": "PropertyValue",
      "name": "field_estimates_no_award",
      "description": "Estimates No Award",
      "valueType": "string",
      "unitText": "Number and percent"
    },
    {
      "@type": "PropertyValue",
      "name": "field_estimates_share_",
      "description": "Estimates Share ",
      "valueType": "string",
      "unitText": "Number and percent"
    },
    {
      "@type": "PropertyValue",
      "name": "field_standard_errors_nsf_award",
      "description": "Standard Errors Nsf Award",
      "valueType": "string",
      "unitText": "Number and percent"
    },
    {
      "@type": "PropertyValue",
      "name": "field_standard_errors_no_award",
      "description": "Standard Errors No Award",
      "valueType": "string",
      "unitText": "Number and percent"
    },
    {
      "@type": "PropertyValue",
      "name": "field_standard_errors_share_",
      "description": "Standard Errors Share ",
      "valueType": "string",
      "unitText": "Number and percent"
    }
  ],
  "structuralType": "table",
  "transformationNotes": {
    "cleaningOperations": [
      "HTML tag removal",
      "Hierarchy normalization",
      "Special value handling"
    ],
    "specialValues": {
      "i": "imputed value",
      "r": "revised value"
    }
  },
  "notes": "Other includes American Indian or Alaska Native, Native Hawaiian or Pacific Islander, and multiple race. Hispanic may be any race; Asian, Black, and White exclude Hispanic origin.",
  "sources": "National Center for Science and Engineering Statistics, Survey of Doctorate Recipients, 2015, linked to the public NSF Awards Database (https://www.nsf.gov/awardsearch/download.jsp)."
}