{
  "@context": "https://schema.org/",
  "@type": "Dataset",
  "dct:conformsTo": "http://mlcommons.org/croissant/1.0",
  "name": "Institutional rankings for graduate students: 2020",
  "identifier": "NCSES-6046",
  "description": "Institutional rankings for graduate students: 2020",
  "url": "https://example.org/datasets/ncses/tables/6046",
  "table_number": "5-4a",
  "creator": {
    "@type": "Organization",
    "name": "National Center for Science and Engineering Statistics"
  },
  "schemaVersion": "https://w3id.org/croissant/schema/1.0",
  "distribution": {
    "@type": "DataDownload",
    "encodingFormat": "text/csv",
    "contentUrl": "https://example.org/datasets/ncses/tables/6046/data.csv"
  },
  "variableMeasured": [
    {
      "@type": "PropertyValue",
      "name": "_b_institution_b",
      "description": "Institution hierarchy",
      "valueType": "string",
      "additionalProperty": [
        {
          "name": "hierarchical",
          "value": "true"
        },
        {
          "name": "maxHierarchyDepth",
          "value": "2"
        },
        {
          "name": "levelColumns",
          "value": "_b_institution_b_level_1, _b_institution_b_level_2"
        },
        {
          "name": "fullPathColumn",
          "value": "_b_institution_b_full_path"
        }
      ]
    },
    {
      "@type": "PropertyValue",
      "name": "field_all_graduate_students_rank",
      "description": "All Graduate Students Rank",
      "valueType": "string",
      "unitText": "Number"
    },
    {
      "@type": "PropertyValue",
      "name": "field_all_graduate_students_total",
      "description": "All Graduate Students Total",
      "valueType": "string",
      "unitText": "Number"
    },
    {
      "@type": "PropertyValue",
      "name": "field_all_graduate_students_science",
      "description": "All Graduate Students Science",
      "valueType": "string",
      "unitText": "Number"
    },
    {
      "@type": "PropertyValue",
      "name": "field_all_graduate_students_engineering",
      "description": "All Graduate Students Engineering",
      "valueType": "string",
      "unitText": "Number"
    },
    {
      "@type": "PropertyValue",
      "name": "field_all_graduate_students_health",
      "description": "All Graduate Students Health",
      "valueType": "string",
      "unitText": "Number"
    },
    {
      "@type": "PropertyValue",
      "name": "field_full_time_students_rank",
      "description": "Full Time Students Rank",
      "valueType": "string",
      "unitText": "Number"
    },
    {
      "@type": "PropertyValue",
      "name": "field_full_time_students_total",
      "description": "Full Time Students Total",
      "valueType": "string",
      "unitText": "Number"
    },
    {
      "@type": "PropertyValue",
      "name": "field_full_time_students_science",
      "description": "Full Time Students Science",
      "valueType": "string",
      "unitText": "Number"
    },
    {
      "@type": "PropertyValue",
      "name": "field_full_time_students_engineering",
      "description": "Full Time Students Engineering",
      "valueType": "string",
      "unitText": "Number"
    },
    {
      "@type": "PropertyValue",
      "name": "field_full_time_students_health",
      "description": "Full Time Students Health",
      "valueType": "string",
      "unitText": "Number"
    },
    {
      "@type": "PropertyValue",
      "name": "field_part_time_students_rank",
      "description": "Part Time Students Rank",
      "valueType": "string",
      "unitText": "Number"
    },
    {
      "@type": "PropertyValue",
      "name": "field_part_time_students_total",
      "description": "Part Time Students Total",
      "valueType": "string",
      "unitText": "Number"
    },
    {
      "@type": "PropertyValue",
      "name": "field_part_time_students_science",
      "description": "Part Time Students Science",
      "valueType": "string",
      "unitText": "Number"
    },
    {
      "@type": "PropertyValue",
      "name": "field_part_time_students_engineering",
      "description": "Part Time Students Engineering",
      "valueType": "string",
      "unitText": "Number"
    },
    {
      "@type": "PropertyValue",
      "name": "field_part_time_students_health",
      "description": "Part Time Students Health",
      "valueType": "string",
      "unitText": "Number"
    }
  ],
  "structuralType": "table",
  "transformationNotes": {
    "cleaningOperations": [
      "HTML tag removal",
      "Hierarchy normalization",
      "Special value handling"
    ],
    "specialValues": {
      "i": "imputed value",
      "r": "revised value",
      "D": "suppressed to avoid disclosure of confidential information"
    }
  },
  "notes": "Sorted by overall number of graduate students. Tied institutions are ranked first by number of doctoral students and then alphabetically. For more information on the mapping of Survey of Graduate Students and Postdoctorates in Science and Engineering fields and codes, see technical table A-17.",
  "sources": "National Center for Science and Engineering Statistics, Survey of Graduate Students and Postdoctorates in Science and Engineering, 2020."
}