{
  "@context": "https://schema.org/",
  "@type": "Dataset",
  "dct:conformsTo": "http://mlcommons.org/croissant/1.0",
  "name": "Bachelor's degrees awarded by all institutions and by tribal colleges and universities to American Indian or Alaska Native U.S. citizens and permanent residents, by field: 2006&#8211;16",
  "identifier": "NCSES-1153",
  "description": "Bachelor's degrees awarded by all institutions and by tribal colleges and universities to American Indian or Alaska Native U.S. citizens and permanent residents, by field: 2006&#8211;16",
  "url": "https://example.org/datasets/ncses/tables/1153",
  "table_number": "5-10",
  "creator": {
    "@type": "Organization",
    "name": "National Center for Science and Engineering Statistics"
  },
  "schemaVersion": "https://w3id.org/croissant/schema/1.0",
  "distribution": {
    "@type": "DataDownload",
    "encodingFormat": "text/csv",
    "contentUrl": "https://example.org/datasets/ncses/tables/1153/data.csv"
  },
  "variableMeasured": [
    {
      "@type": "PropertyValue",
      "name": "institution_type_and_field",
      "description": "Institution type and field hierarchy",
      "valueType": "string",
      "additionalProperty": [
        {
          "name": "hierarchical",
          "value": "true"
        },
        {
          "name": "maxHierarchyDepth",
          "value": "6"
        },
        {
          "name": "levelColumns",
          "value": "institution_type_and_field_level_1, institution_type_and_field_level_2, institution_type_and_field_level_3, institution_type_and_field_level_4, institution_type_and_field_level_5, institution_type_and_field_level_6"
        },
        {
          "name": "fullPathColumn",
          "value": "institution_type_and_field_full_path"
        }
      ]
    },
    {
      "@type": "PropertyValue",
      "name": "field_2006",
      "description": "2006",
      "valueType": "string",
      "unitText": "Number and percent"
    },
    {
      "@type": "PropertyValue",
      "name": "field_2007",
      "description": "2007",
      "valueType": "string",
      "unitText": "Number and percent"
    },
    {
      "@type": "PropertyValue",
      "name": "field_2008",
      "description": "2008",
      "valueType": "string",
      "unitText": "Number and percent"
    },
    {
      "@type": "PropertyValue",
      "name": "field_2009",
      "description": "2009",
      "valueType": "string",
      "unitText": "Number and percent"
    },
    {
      "@type": "PropertyValue",
      "name": "field_2010",
      "description": "2010",
      "valueType": "string",
      "unitText": "Number and percent"
    },
    {
      "@type": "PropertyValue",
      "name": "field_2011",
      "description": "2011",
      "valueType": "string",
      "unitText": "Number and percent"
    },
    {
      "@type": "PropertyValue",
      "name": "field_2012",
      "description": "2012",
      "valueType": "string",
      "unitText": "Number and percent"
    },
    {
      "@type": "PropertyValue",
      "name": "field_2013",
      "description": "2013",
      "valueType": "string",
      "unitText": "Number and percent"
    },
    {
      "@type": "PropertyValue",
      "name": "field_2014",
      "description": "2014",
      "valueType": "string",
      "unitText": "Number and percent"
    },
    {
      "@type": "PropertyValue",
      "name": "field_2015",
      "description": "2015",
      "valueType": "string",
      "unitText": "Number and percent"
    },
    {
      "@type": "PropertyValue",
      "name": "field_2016",
      "description": "2016",
      "valueType": "string",
      "unitText": "Number and percent"
    }
  ],
  "structuralType": "table",
  "transformationNotes": {
    "cleaningOperations": [
      "HTML tag removal",
      "Hierarchy normalization",
      "Special value handling"
    ],
    "specialValues": {
      "i": "imputed value",
      "r": "revised value"
    }
  },
  "notes": "Data are based on degree-granting institutions eligible to participate in Title IV federal financial aid programs and do not match previously published data that were based on accredited higher education institutions.",
  "sources": "National Science Foundation, National Center for Science and Engineering Statistics, special tabulations of U.S. Department of Education, National Center for Education Statistics, Integrated Postsecondary Education Data System, Completions Survey, unrevised provisional release data."
}